{"id":"okinawa-midterm-indicator-evidence-part-3","prefecture_code":"47","packet_count":94,"packets":[{"id":"okinawa-midterm-evidence-189","subject_id":"okinawa-midterm-indicator-189","source_url":"https://www.pref.okinawa.jp/_res/projects/default_project/_page_/001/034/436/7_tyukijisshikeikaku_r2.pdf","source_pdf_page":38,"source_table_row":2,"claims":[{"field":"policy","value_original":"３－（２）－エ－① ICTによる新たな観 光体験の創出促進 及び観光施設等に おける利便性向上"},{"field":"indicator_name","value_original":"リアルタイムな情報を オープンデータ化して 公開している観光施 設数"},{"field":"baseline","value_original":"０施設 （R３年度）"},{"field":"target_r9","value_original":"４施設"},{"field":"national_current","value_original":"－"}],"review_status":"reviewed"},{"id":"okinawa-midterm-evidence-190","subject_id":"okinawa-midterm-indicator-190","source_url":"https://www.pref.okinawa.jp/_res/projects/default_project/_page_/001/034/436/7_tyukijisshikeikaku_r2.pdf","source_pdf_page":38,"source_table_row":3,"claims":[{"field":"policy","value_original":"３－（２）－エ－② 世界のビジネス パーソン等が訪れる ワーケーション拠点 の形成"},{"field":"indicator_name","value_original":"ワーケーションを行っ た来県者の延べ泊数"},{"field":"baseline","value_original":"300,570人泊 （R３年度）"},{"field":"target_r9","value_original":"649,000人泊"},{"field":"national_current","value_original":"－"}],"review_status":"reviewed"},{"id":"okinawa-midterm-evidence-191","subject_id":"okinawa-midterm-indicator-191","source_url":"https://www.pref.okinawa.jp/_res/projects/default_project/_page_/001/034/436/7_tyukijisshikeikaku_r2.pdf","source_pdf_page":38,"source_table_row":4,"claims":[{"field":"policy","value_original":"３－（２）－エ－③ データを活用した戦 略的なマーケティン グの推進"},{"field":"indicator_name","value_original":"国内・国外観光客の 行動歴・販売データの サンプル件数"},{"field":"baseline","value_original":"5,000件 （R３年度）"},{"field":"target_r9","value_original":"70,000件"},{"field":"national_current","value_original":"－"}],"review_status":"reviewed"},{"id":"okinawa-midterm-evidence-192","subject_id":"okinawa-midterm-indicator-192","source_url":"https://www.pref.okinawa.jp/_res/projects/default_project/_page_/001/034/436/7_tyukijisshikeikaku_r2.pdf","source_pdf_page":38,"source_table_row":5,"claims":[{"field":"policy","value_original":"３－（２）－エ－④ 観光二次交通の利 便性向上及び利用 促進"},{"field":"indicator_name","value_original":"旅行中に利用した公 共交通機関の割合"},{"field":"baseline","value_original":"67.3％ （R３年度）"},{"field":"target_r9","value_original":"80.0%"},{"field":"national_current","value_original":"－"}],"review_status":"reviewed"},{"id":"okinawa-midterm-evidence-193","subject_id":"okinawa-midterm-indicator-193","source_url":"https://www.pref.okinawa.jp/_res/projects/default_project/_page_/001/034/436/7_tyukijisshikeikaku_r2.pdf","source_pdf_page":38,"source_table_row":6,"claims":[{"field":"policy","value_original":"３－（２）－オ－① MICE振興とビジネ スツーリズムの推進"},{"field":"indicator_name","value_original":"MICE開催による経済 効果（直接効果）"},{"field":"baseline","value_original":"36億円 （R３年）"},{"field":"target_r9","value_original":"635億円"},{"field":"national_current","value_original":"－"}],"review_status":"reviewed"},{"id":"okinawa-midterm-evidence-194","subject_id":"okinawa-midterm-indicator-194","source_url":"https://www.pref.okinawa.jp/_res/projects/default_project/_page_/001/034/436/7_tyukijisshikeikaku_r2.pdf","source_pdf_page":39,"source_table_row":1,"claims":[{"field":"policy","value_original":"３－（２）－オ－② マリンタウンMICEエ リアを核とした全県 的なMICE受入体制 の整備"},{"field":"indicator_name","value_original":"1,000人以上のMICE 開催件数"},{"field":"baseline","value_original":"６件 （R３年）"},{"field":"target_r9","value_original":"141件"},{"field":"national_current","value_original":"－"}],"review_status":"reviewed"},{"id":"okinawa-midterm-evidence-195","subject_id":"okinawa-midterm-indicator-195","source_url":"https://www.pref.okinawa.jp/_res/projects/default_project/_page_/001/034/436/7_tyukijisshikeikaku_r2.pdf","source_pdf_page":39,"source_table_row":2,"claims":[{"field":"policy","value_original":"３－（２）－オ－③ MICEを活用した関 連産業の振興"},{"field":"indicator_name","value_original":"MICE開催による経済 波及効果（間接効果）"},{"field":"baseline","value_original":"43億円 （R３年）"},{"field":"target_r9","value_original":"679億円"},{"field":"national_current","value_original":"－"}],"review_status":"reviewed"},{"id":"okinawa-midterm-evidence-196","subject_id":"okinawa-midterm-indicator-196","source_url":"https://www.pref.okinawa.jp/_res/projects/default_project/_page_/001/034/436/7_tyukijisshikeikaku_r2.pdf","source_pdf_page":39,"source_table_row":3,"claims":[{"field":"policy","value_original":"３－（３）－ア－① 県内情報通信関連 産業と他産業連携 による新たなビジネ スモデルの創出"},{"field":"indicator_name","value_original":"情報通信産業におけ る従業者１人当たりの 売上額"},{"field":"baseline","value_original":"1,093万円 （R３年度）"},{"field":"target_r9","value_original":"1,238万円"},{"field":"national_current","value_original":"－"}],"review_status":"reviewed"},{"id":"okinawa-midterm-evidence-197","subject_id":"okinawa-midterm-indicator-197","source_url":"https://www.pref.okinawa.jp/_res/projects/default_project/_page_/001/034/436/7_tyukijisshikeikaku_r2.pdf","source_pdf_page":39,"source_table_row":4,"claims":[{"field":"policy","value_original":"３－（３）－ア－② デジタル技術を活用 したスタートアップや ビジネスイノベー ションの促進"},{"field":"indicator_name","value_original":"デジタル技術を活用し たスタートアップ等の 支援件数（累計）"},{"field":"baseline","value_original":"10件 （R４年度）"},{"field":"target_r9","value_original":"60件"},{"field":"national_current","value_original":"－"}],"review_status":"reviewed"},{"id":"okinawa-midterm-evidence-198","subject_id":"okinawa-midterm-indicator-198","source_url":"https://www.pref.okinawa.jp/_res/projects/default_project/_page_/001/034/436/7_tyukijisshikeikaku_r2.pdf","source_pdf_page":39,"source_table_row":5,"claims":[{"field":"policy","value_original":"３－（３）－アー③ 県内外における市 場開拓の強化"},{"field":"indicator_name","value_original":"IT見本市への参加企 業数"},{"field":"baseline","value_original":"107社 （R３年度）"},{"field":"target_r9","value_original":"140社"},{"field":"national_current","value_original":"－"}],"review_status":"reviewed"},{"id":"okinawa-midterm-evidence-199","subject_id":"okinawa-midterm-indicator-199","source_url":"https://www.pref.okinawa.jp/_res/projects/default_project/_page_/001/034/436/7_tyukijisshikeikaku_r2.pdf","source_pdf_page":39,"source_table_row":6,"claims":[{"field":"policy","value_original":"３－（３）－イ－① 先端ICTを活用し新 ビジネス・サービス を展開する企業の 誘致・集積"},{"field":"indicator_name","value_original":"情報通信産業振興地 域・特区内で新たに立 地・創業したIT企業数 （累計）"},{"field":"baseline","value_original":"０社 （※R３年度末をゼロ に設定）"},{"field":"target_r9","value_original":"180社"},{"field":"national_current","value_original":"－"}],"review_status":"reviewed"},{"id":"okinawa-midterm-evidence-200","subject_id":"okinawa-midterm-indicator-200","source_url":"https://www.pref.okinawa.jp/_res/projects/default_project/_page_/001/034/436/7_tyukijisshikeikaku_r2.pdf","source_pdf_page":40,"source_table_row":1,"claims":[{"field":"policy","value_original":"３－（３）－イ－② 情報通信産業集積 拠点の機能強化と 情報通信基盤の利 用促進"},{"field":"indicator_name","value_original":"沖縄IT津梁パーク入 居企業数及び就業者 数"},{"field":"baseline","value_original":"38社、2,285人 （R３年度）"},{"field":"target_r9","value_original":"45社、3,200人"},{"field":"national_current","value_original":"－"}],"review_status":"reviewed"},{"id":"okinawa-midterm-evidence-201","subject_id":"okinawa-midterm-indicator-201","source_url":"https://www.pref.okinawa.jp/_res/projects/default_project/_page_/001/034/436/7_tyukijisshikeikaku_r2.pdf","source_pdf_page":40,"source_table_row":2,"claims":[{"field":"policy","value_original":"３－（４）－ア－① 国際航空物流ハブ としての機能強化"},{"field":"indicator_name","value_original":"貨物輸送を行う国際 航空路線数"},{"field":"baseline","value_original":"０路線 （R３年度）"},{"field":"target_r9","value_original":"６路線"},{"field":"national_current","value_original":"－"}],"review_status":"reviewed"},{"id":"okinawa-midterm-evidence-202","subject_id":"okinawa-midterm-indicator-202","source_url":"https://www.pref.okinawa.jp/_res/projects/default_project/_page_/001/034/436/7_tyukijisshikeikaku_r2.pdf","source_pdf_page":40,"source_table_row":3,"claims":[{"field":"policy","value_original":"３－（４）－ア－② 国際流通港湾機能 の強化"},{"field":"indicator_name","value_original":"那覇港公共国際コン テナターミナルの取扱 貨物量"},{"field":"baseline","value_original":"7.2万TEU （R３年度）"},{"field":"target_r9","value_original":"約8.8万TEU"},{"field":"national_current","value_original":"約25万TEU （R３年） ※全国港湾の外貿 コンテナ取扱貨物量 (上位72位までの平 均)"}],"review_status":"reviewed"},{"id":"okinawa-midterm-evidence-203","subject_id":"okinawa-midterm-indicator-203","source_url":"https://www.pref.okinawa.jp/_res/projects/default_project/_page_/001/034/436/7_tyukijisshikeikaku_r2.pdf","source_pdf_page":40,"source_table_row":4,"claims":[{"field":"policy","value_original":"３－（４）－ア－③ 物流コスト低減に向 けた国際航路・空路 拡充の取組及び物 流対策の強化"},{"field":"indicator_name","value_original":"那覇空港における国 際貨物量及び那覇港 における定期外国航 路（海外）寄港地数"},{"field":"baseline","value_original":"那覇空港における 国際貨物量0.2万ト ン 那覇港における定 期外国航路（海外） 寄港地数13寄港地 （R３年度）"},{"field":"target_r9","value_original":"那覇空港における 国際貨物量７万トン 那覇港における定 期外国航路（海外） 寄港地数15寄港地"},{"field":"national_current","value_original":"成田空港185万ト ン、関西国際空港72 万トン （R５年度） 定期外国航路数 820便/週 （R元年）"}],"review_status":"reviewed"},{"id":"okinawa-midterm-evidence-204","subject_id":"okinawa-midterm-indicator-204","source_url":"https://www.pref.okinawa.jp/_res/projects/default_project/_page_/001/034/436/7_tyukijisshikeikaku_r2.pdf","source_pdf_page":40,"source_table_row":5,"claims":[{"field":"policy","value_original":"３－（４）－ア－④ 空港・港湾へのアク セス強化に向けた 陸上輸送の基盤整 備"},{"field":"indicator_name","value_original":"那覇港～中城湾港新 港地区の所要時間・ 那覇空港～中城湾港 新港地区の所要時間"},{"field":"baseline","value_original":"那覇港～中城湾港 45分 那覇空港～中城湾 港 50分 （R３年度）"},{"field":"target_r9","value_original":"那覇港～中城湾港 40分 那覇空港～中城湾 港 42分"},{"field":"national_current","value_original":"－"}],"review_status":"reviewed"},{"id":"okinawa-midterm-evidence-205","subject_id":"okinawa-midterm-indicator-205","source_url":"https://www.pref.okinawa.jp/_res/projects/default_project/_page_/001/034/436/7_tyukijisshikeikaku_r2.pdf","source_pdf_page":41,"source_table_row":1,"claims":[{"field":"policy","value_original":"３－（４）－イ－① 高付加価値製品を 製造する企業等の 誘致"},{"field":"indicator_name","value_original":"臨空・臨港型産業にお ける新規立地企業数 （累計）"},{"field":"baseline","value_original":"０社 （※R３年度末をゼロ に設定） （R３年度）"},{"field":"target_r9","value_original":"166社"},{"field":"national_current","value_original":"－"}],"review_status":"reviewed"},{"id":"okinawa-midterm-evidence-206","subject_id":"okinawa-midterm-indicator-206","source_url":"https://www.pref.okinawa.jp/_res/projects/default_project/_page_/001/034/436/7_tyukijisshikeikaku_r2.pdf","source_pdf_page":41,"source_table_row":2,"claims":[{"field":"policy","value_original":"３－（４）－イ－② 航空関連産業クラス ターの形成"},{"field":"indicator_name","value_original":"航空関連産業企業数 （累計）"},{"field":"baseline","value_original":"７社 （R３年度）"},{"field":"target_r9","value_original":"16社"},{"field":"national_current","value_original":"－"}],"review_status":"reviewed"},{"id":"okinawa-midterm-evidence-207","subject_id":"okinawa-midterm-indicator-207","source_url":"https://www.pref.okinawa.jp/_res/projects/default_project/_page_/001/034/436/7_tyukijisshikeikaku_r2.pdf","source_pdf_page":41,"source_table_row":3,"claims":[{"field":"policy","value_original":"３－（４）－イ－③ 離島空港における 航空・宇宙関連事業 の展開"},{"field":"indicator_name","value_original":"離島空港の区域内に おける企業使用面積 （累計）"},{"field":"baseline","value_original":"3.7ha （R３年度）"},{"field":"target_r9","value_original":"22.3ha"},{"field":"national_current","value_original":"－"}],"review_status":"reviewed"},{"id":"okinawa-midterm-evidence-208","subject_id":"okinawa-midterm-indicator-208","source_url":"https://www.pref.okinawa.jp/_res/projects/default_project/_page_/001/034/436/7_tyukijisshikeikaku_r2.pdf","source_pdf_page":41,"source_table_row":4,"claims":[{"field":"policy","value_original":"３－（４）－ウー① 海外展開に向けた 総合的な支援"},{"field":"indicator_name","value_original":"県内輸出事業者等に よる沖縄からの年間 輸出額"},{"field":"baseline","value_original":"19,346百万円 （R３年）"},{"field":"target_r9","value_original":"24,198百万円"},{"field":"national_current","value_original":"－"}],"review_status":"reviewed"},{"id":"okinawa-midterm-evidence-209","subject_id":"okinawa-midterm-indicator-209","source_url":"https://www.pref.okinawa.jp/_res/projects/default_project/_page_/001/034/436/7_tyukijisshikeikaku_r2.pdf","source_pdf_page":41,"source_table_row":5,"claims":[{"field":"policy","value_original":"３－（４）－ウ－② アジアをはじめとす る海外をつなぐビジ ネス交流拠点の形 成"},{"field":"indicator_name","value_original":"MICE開催件数の内展 示会等（E）開催件数"},{"field":"baseline","value_original":"38件 （R３年度）"},{"field":"target_r9","value_original":"200件"},{"field":"national_current","value_original":"－"}],"review_status":"reviewed"},{"id":"okinawa-midterm-evidence-210","subject_id":"okinawa-midterm-indicator-210","source_url":"https://www.pref.okinawa.jp/_res/projects/default_project/_page_/001/034/436/7_tyukijisshikeikaku_r2.pdf","source_pdf_page":41,"source_table_row":6,"claims":[{"field":"policy","value_original":"３－（５）－ア－① OIST等を核とした共 同研究の推進等に よるイノベーション 創出拠点の形成"},{"field":"indicator_name","value_original":"大学等が共同研究費 として民間企業から受 け入れた金額"},{"field":"baseline","value_original":"160百万円 （R３年度）"},{"field":"target_r9","value_original":"347百万円"},{"field":"national_current","value_original":"89,266百万円 （R３年度）"}],"review_status":"reviewed"},{"id":"okinawa-midterm-evidence-211","subject_id":"okinawa-midterm-indicator-211","source_url":"https://www.pref.okinawa.jp/_res/projects/default_project/_page_/001/034/436/7_tyukijisshikeikaku_r2.pdf","source_pdf_page":42,"source_table_row":1,"claims":[{"field":"policy","value_original":"３－（５）－ア－② 研究成果等の知的 財産化・技術移転の 推進"},{"field":"indicator_name","value_original":"県内からの特許等出 願件数（累計）"},{"field":"baseline","value_original":"1,074件 （R３年）"},{"field":"target_r9","value_original":"6,655件"},{"field":"national_current","value_original":"374,834件 （R５年）"}],"review_status":"reviewed"},{"id":"okinawa-midterm-evidence-212","subject_id":"okinawa-midterm-indicator-212","source_url":"https://www.pref.okinawa.jp/_res/projects/default_project/_page_/001/034/436/7_tyukijisshikeikaku_r2.pdf","source_pdf_page":42,"source_table_row":2,"claims":[{"field":"policy","value_original":"３－（５）－ア－③ 大学発ベンチャー等 の創出と高度研究 人材等の活用等に 向けた環境整備"},{"field":"indicator_name","value_original":"大学発ベンチャー等 創出数（累計）"},{"field":"baseline","value_original":"24社 （R３年度）"},{"field":"target_r9","value_original":"51社"},{"field":"national_current","value_original":"4,288社 （R５年度）"}],"review_status":"reviewed"},{"id":"okinawa-midterm-evidence-213","subject_id":"okinawa-midterm-indicator-213","source_url":"https://www.pref.okinawa.jp/_res/projects/default_project/_page_/001/034/436/7_tyukijisshikeikaku_r2.pdf","source_pdf_page":42,"source_table_row":3,"claims":[{"field":"policy","value_original":"３－（５）－ア－④ 社会課題解決型の 科学技術プロジェク ト創出支援"},{"field":"indicator_name","value_original":"大学等発社会課題解 決型の科学技術プロ ジェクト実施件数（累 計）"},{"field":"baseline","value_original":"４件 （R４年度）"},{"field":"target_r9","value_original":"28件"},{"field":"national_current","value_original":"－"}],"review_status":"reviewed"},{"id":"okinawa-midterm-evidence-214","subject_id":"okinawa-midterm-indicator-214","source_url":"https://www.pref.okinawa.jp/_res/projects/default_project/_page_/001/034/436/7_tyukijisshikeikaku_r2.pdf","source_pdf_page":42,"source_table_row":4,"claims":[{"field":"policy","value_original":"３－（５）－イ－① 企業等による研究 開発、販路開拓、人 材育成等の促進"},{"field":"indicator_name","value_original":"バイオベンチャー企業 数"},{"field":"baseline","value_original":"47社 （R３年度）"},{"field":"target_r9","value_original":"90社"},{"field":"national_current","value_original":"2,116社 （R元年度）"}],"review_status":"reviewed"},{"id":"okinawa-midterm-evidence-215","subject_id":"okinawa-midterm-indicator-215","source_url":"https://www.pref.okinawa.jp/_res/projects/default_project/_page_/001/034/436/7_tyukijisshikeikaku_r2.pdf","source_pdf_page":42,"source_table_row":5,"claims":[{"field":"policy","value_original":"３－（５）－イ－② 先端医療分野にお ける実用化の促進"},{"field":"indicator_name","value_original":"先端医療技術の実用 化に向けた試験等実 施件数（累計）"},{"field":"baseline","value_original":"６件 （R３年度）"},{"field":"target_r9","value_original":"12件"},{"field":"national_current","value_original":"－"}],"review_status":"reviewed"},{"id":"okinawa-midterm-evidence-216","subject_id":"okinawa-midterm-indicator-216","source_url":"https://www.pref.okinawa.jp/_res/projects/default_project/_page_/001/034/436/7_tyukijisshikeikaku_r2.pdf","source_pdf_page":42,"source_table_row":6,"claims":[{"field":"policy","value_original":"３－（５）－イ－③ 健康・医療分野を軸 とした産業拠点の形 成"},{"field":"indicator_name","value_original":"バイオ関連企業等の 企業数"},{"field":"baseline","value_original":"69社 （R３年度）"},{"field":"target_r9","value_original":"122社"},{"field":"national_current","value_original":"－"}],"review_status":"reviewed"},{"id":"okinawa-midterm-evidence-217","subject_id":"okinawa-midterm-indicator-217","source_url":"https://www.pref.okinawa.jp/_res/projects/default_project/_page_/001/034/436/7_tyukijisshikeikaku_r2.pdf","source_pdf_page":43,"source_table_row":1,"claims":[{"field":"policy","value_original":"３－（６）－ア－① 起業家の育成"},{"field":"indicator_name","value_original":"起業家育成数"},{"field":"baseline","value_original":"109人 （R４年度）"},{"field":"target_r9","value_original":"100人"},{"field":"national_current","value_original":"－"}],"review_status":"reviewed"},{"id":"okinawa-midterm-evidence-218","subject_id":"okinawa-midterm-indicator-218","source_url":"https://www.pref.okinawa.jp/_res/projects/default_project/_page_/001/034/436/7_tyukijisshikeikaku_r2.pdf","source_pdf_page":43,"source_table_row":2,"claims":[{"field":"policy","value_original":"３－（６）－ア－② 創業・成長の支援体 制の構築"},{"field":"indicator_name","value_original":"スタートアップの資金 調達額（累計）"},{"field":"baseline","value_original":"76.0億円 （R３年）"},{"field":"target_r9","value_original":"359.7億円"},{"field":"national_current","value_original":"－"}],"review_status":"reviewed"},{"id":"okinawa-midterm-evidence-219","subject_id":"okinawa-midterm-indicator-219","source_url":"https://www.pref.okinawa.jp/_res/projects/default_project/_page_/001/034/436/7_tyukijisshikeikaku_r2.pdf","source_pdf_page":43,"source_table_row":3,"claims":[{"field":"policy","value_original":"３－（６）－ア－③ スタートアップ等と 大手企業・金融機 関・研究機関・大学 等との連携促進"},{"field":"indicator_name","value_original":"支援したスタートアッ プによる社会提供した ソリューション・プロダ クト件数"},{"field":"baseline","value_original":"５件 （Ｒ４年度）"},{"field":"target_r9","value_original":"５件"},{"field":"national_current","value_original":"－"}],"review_status":"reviewed"},{"id":"okinawa-midterm-evidence-220","subject_id":"okinawa-midterm-indicator-220","source_url":"https://www.pref.okinawa.jp/_res/projects/default_project/_page_/001/034/436/7_tyukijisshikeikaku_r2.pdf","source_pdf_page":43,"source_table_row":4,"claims":[{"field":"policy","value_original":"３－（６）－ア－④ 金融関連産業の集 積促進"},{"field":"indicator_name","value_original":"経済金融活性化特別 地区立地企業数（金 融関連企業）"},{"field":"baseline","value_original":"14社 （R３年度）"},{"field":"target_r9","value_original":"26社"},{"field":"national_current","value_original":"－"}],"review_status":"reviewed"},{"id":"okinawa-midterm-evidence-221","subject_id":"okinawa-midterm-indicator-221","source_url":"https://www.pref.okinawa.jp/_res/projects/default_project/_page_/001/034/436/7_tyukijisshikeikaku_r2.pdf","source_pdf_page":43,"source_table_row":5,"claims":[{"field":"policy","value_original":"３－（６）－イ－① 文化芸術に関する 産業の創出・振興"},{"field":"indicator_name","value_original":"文化資源を活用したビ ジネスの自走化件数 （累計）"},{"field":"baseline","value_original":"３件 （R４年度）"},{"field":"target_r9","value_original":"22件"},{"field":"national_current","value_original":"－"}],"review_status":"reviewed"},{"id":"okinawa-midterm-evidence-222","subject_id":"okinawa-midterm-indicator-222","source_url":"https://www.pref.okinawa.jp/_res/projects/default_project/_page_/001/034/436/7_tyukijisshikeikaku_r2.pdf","source_pdf_page":43,"source_table_row":6,"claims":[{"field":"policy","value_original":"３－（６）－イ－② 空手を活用した産業 の創出・振興"},{"field":"indicator_name","value_original":"空手を組み込んだ体 験型観光プログラム や商品等の開発件数"},{"field":"baseline","value_original":"０件 （R４年度）"},{"field":"target_r9","value_original":"２件"},{"field":"national_current","value_original":"－"}],"review_status":"reviewed"},{"id":"okinawa-midterm-evidence-223","subject_id":"okinawa-midterm-indicator-223","source_url":"https://www.pref.okinawa.jp/_res/projects/default_project/_page_/001/034/436/7_tyukijisshikeikaku_r2.pdf","source_pdf_page":44,"source_table_row":1,"claims":[{"field":"policy","value_original":"３－（６）－イ－③ eスポーツを活用し た新たな展開"},{"field":"indicator_name","value_original":"県が支援したeスポー ツイベント・大会の観 客動員数"},{"field":"baseline","value_original":"０人 （R３年度）"},{"field":"target_r9","value_original":"1,500人"},{"field":"national_current","value_original":"－"}],"review_status":"reviewed"},{"id":"okinawa-midterm-evidence-224","subject_id":"okinawa-midterm-indicator-224","source_url":"https://www.pref.okinawa.jp/_res/projects/default_project/_page_/001/034/436/7_tyukijisshikeikaku_r2.pdf","source_pdf_page":44,"source_table_row":2,"claims":[{"field":"policy","value_original":"３－（６）－イ－④ 健康サービス産業 の振興"},{"field":"indicator_name","value_original":"ウェルネスツーリズム を推進する観光コンテ ンツ開発件数（累計）"},{"field":"baseline","value_original":"１件 （R４年度）"},{"field":"target_r9","value_original":"６件"},{"field":"national_current","value_original":"－"}],"review_status":"reviewed"},{"id":"okinawa-midterm-evidence-225","subject_id":"okinawa-midterm-indicator-225","source_url":"https://www.pref.okinawa.jp/_res/projects/default_project/_page_/001/034/436/7_tyukijisshikeikaku_r2.pdf","source_pdf_page":44,"source_table_row":3,"claims":[{"field":"policy","value_original":"３－（７）－ア－① 野菜・果樹・花き類 等の生産振興"},{"field":"indicator_name","value_original":"野菜・果樹・花き類の 生産量（園芸品目）"},{"field":"baseline","value_original":"（野菜）49,245トン （果樹）14,208トン （花き）248,512千本 （R３年度）"},{"field":"target_r9","value_original":"（野菜）60,444トン （果樹）20,258トン （花き）308,773千本"},{"field":"national_current","value_original":"（野菜）12,842千トン （果樹）2,318千トン （花き）3,920,100千 本 （R４年度）"}],"review_status":"reviewed"},{"id":"okinawa-midterm-evidence-226","subject_id":"okinawa-midterm-indicator-226","source_url":"https://www.pref.okinawa.jp/_res/projects/default_project/_page_/001/034/436/7_tyukijisshikeikaku_r2.pdf","source_pdf_page":44,"source_table_row":4,"claims":[{"field":"policy","value_original":"３－（７）－ア－② 肉用牛・養豚の生産 振興"},{"field":"indicator_name","value_original":"家畜頭数（肉用牛、 豚）"},{"field":"baseline","value_original":"113,292頭 （R３年度）"},{"field":"target_r9","value_original":"128,884頭"},{"field":"national_current","value_original":"4,403,800頭 （R３年度）"}],"review_status":"reviewed"},{"id":"okinawa-midterm-evidence-227","subject_id":"okinawa-midterm-indicator-227","source_url":"https://www.pref.okinawa.jp/_res/projects/default_project/_page_/001/034/436/7_tyukijisshikeikaku_r2.pdf","source_pdf_page":44,"source_table_row":5,"claims":[{"field":"policy","value_original":"３－（７）－ア－③ さとうきび等の安定 品目の生産振興"},{"field":"indicator_name","value_original":"さとうきび生産量"},{"field":"baseline","value_original":"815,426トン （R３年度）"},{"field":"target_r9","value_original":"902,000トン"},{"field":"national_current","value_original":"1,270,550トン （R４年度）"}],"review_status":"reviewed"},{"id":"okinawa-midterm-evidence-228","subject_id":"okinawa-midterm-indicator-228","source_url":"https://www.pref.okinawa.jp/_res/projects/default_project/_page_/001/034/436/7_tyukijisshikeikaku_r2.pdf","source_pdf_page":45,"source_table_row":1,"claims":[{"field":"policy","value_original":"３－（７）－ア－④ 林産物の生産振興"},{"field":"indicator_name","value_original":"きのこ類の生産量"},{"field":"baseline","value_original":"1,377トン (R３年度)"},{"field":"target_r9","value_original":"1,433トン"},{"field":"national_current","value_original":"459,082トン （R４年度）"}],"review_status":"reviewed"},{"id":"okinawa-midterm-evidence-229","subject_id":"okinawa-midterm-indicator-229","source_url":"https://www.pref.okinawa.jp/_res/projects/default_project/_page_/001/034/436/7_tyukijisshikeikaku_r2.pdf","source_pdf_page":45,"source_table_row":2,"claims":[{"field":"policy","value_original":"３－（７）－ア－⑤ 沖縄型のつくり育て る漁業の振興"},{"field":"indicator_name","value_original":"海面養殖業生産量"},{"field":"baseline","value_original":"24,042トン （R３年度）"},{"field":"target_r9","value_original":"26,600トン"},{"field":"national_current","value_original":"911,839トン （R４年度）"}],"review_status":"reviewed"},{"id":"okinawa-midterm-evidence-230","subject_id":"okinawa-midterm-indicator-230","source_url":"https://www.pref.okinawa.jp/_res/projects/default_project/_page_/001/034/436/7_tyukijisshikeikaku_r2.pdf","source_pdf_page":45,"source_table_row":3,"claims":[{"field":"policy","value_original":"３－（７）－ア－⑥ 資源管理型沿岸漁 業の振興"},{"field":"indicator_name","value_original":"海面漁業生産量"},{"field":"baseline","value_original":"14,936トン （R３年度）"},{"field":"target_r9","value_original":"16,100トン"},{"field":"national_current","value_original":"2,950,992トン （R４年度）"}],"review_status":"reviewed"},{"id":"okinawa-midterm-evidence-231","subject_id":"okinawa-midterm-indicator-231","source_url":"https://www.pref.okinawa.jp/_res/projects/default_project/_page_/001/034/436/7_tyukijisshikeikaku_r2.pdf","source_pdf_page":45,"source_table_row":4,"claims":[{"field":"policy","value_original":"３－（７）－イ－① 生産段階の品質管 理の強化と表示の 適正化の推進"},{"field":"indicator_name","value_original":"国のガイドラインに基 づいたGAPの導入経 営体数（累計）"},{"field":"baseline","value_original":"106件 （R３年度）"},{"field":"target_r9","value_original":"136件"},{"field":"national_current","value_original":"7,480件 （R５年度） （※GAP認証取得経 営体数（国内農畜産 業））"}],"review_status":"reviewed"},{"id":"okinawa-midterm-evidence-232","subject_id":"okinawa-midterm-indicator-232","source_url":"https://www.pref.okinawa.jp/_res/projects/default_project/_page_/001/034/436/7_tyukijisshikeikaku_r2.pdf","source_pdf_page":45,"source_table_row":5,"claims":[{"field":"policy","value_original":"３－（７）－イ－② 県産農林水産物の 高度な衛生管理の 推進"},{"field":"indicator_name","value_original":"加工処理施設等の HACCP等の認証取得 割合"},{"field":"baseline","value_original":"畜産施設 14％ 水産施設 ６％ （R３年度）"},{"field":"target_r9","value_original":"畜産施設 57％ 水産施設 ９％"},{"field":"national_current","value_original":"畜産食料品製造業 46.4％ 水産食料品製造業 36.5％ （R３年度）"}],"review_status":"reviewed"},{"id":"okinawa-midterm-evidence-233","subject_id":"okinawa-midterm-indicator-233","source_url":"https://www.pref.okinawa.jp/_res/projects/default_project/_page_/001/034/436/7_tyukijisshikeikaku_r2.pdf","source_pdf_page":46,"source_table_row":1,"claims":[{"field":"policy","value_original":"３－（７）－イ－③ 特殊病害虫等の侵 入防止"},{"field":"indicator_name","value_original":"移動規制を伴う緊急 防除発令数"},{"field":"baseline","value_original":"０件 （R３年度）"},{"field":"target_r9","value_original":"０件"},{"field":"national_current","value_original":"３件 （R５年度）"}],"review_status":"reviewed"},{"id":"okinawa-midterm-evidence-234","subject_id":"okinawa-midterm-indicator-234","source_url":"https://www.pref.okinawa.jp/_res/projects/default_project/_page_/001/034/436/7_tyukijisshikeikaku_r2.pdf","source_pdf_page":46,"source_table_row":2,"claims":[{"field":"policy","value_original":"３－（７）－イ－④ 特定家畜伝染病対 策の強化と徹底"},{"field":"indicator_name","value_original":"特定家畜伝染病の発 生件数"},{"field":"baseline","value_original":"０件 （R３年度）"},{"field":"target_r9","value_original":"０件"},{"field":"national_current","value_original":"16件 （R５年度）"}],"review_status":"reviewed"},{"id":"okinawa-midterm-evidence-235","subject_id":"okinawa-midterm-indicator-235","source_url":"https://www.pref.okinawa.jp/_res/projects/default_project/_page_/001/034/436/7_tyukijisshikeikaku_r2.pdf","source_pdf_page":46,"source_table_row":3,"claims":[{"field":"policy","value_original":"３－（７）－イ－⑤ 環境に配慮した病 害虫防除対策と鳥 獣被害防止対策の 推進"},{"field":"indicator_name","value_original":"総合的病害虫防除技 術実践者数（累計）"},{"field":"baseline","value_original":"192戸 （R３年度）"},{"field":"target_r9","value_original":"197戸"},{"field":"national_current","value_original":"287作物 （H28年度） （※各都道府県で策 定したIPM実践指標 の作物数）"}],"review_status":"reviewed"},{"id":"okinawa-midterm-evidence-236","subject_id":"okinawa-midterm-indicator-236","source_url":"https://www.pref.okinawa.jp/_res/projects/default_project/_page_/001/034/436/7_tyukijisshikeikaku_r2.pdf","source_pdf_page":46,"source_table_row":4,"claims":[{"field":"policy","value_original":"３－（７）－ウ－① 農林水産物の輸送 コストの低減対策及 び総合的な流通の 合理化"},{"field":"indicator_name","value_original":"県外出荷量のうち船 舶輸送での出荷量の 割合"},{"field":"baseline","value_original":"65％ （R３年度）"},{"field":"target_r9","value_original":"70％"},{"field":"national_current","value_original":"－"}],"review_status":"reviewed"},{"id":"okinawa-midterm-evidence-237","subject_id":"okinawa-midterm-indicator-237","source_url":"https://www.pref.okinawa.jp/_res/projects/default_project/_page_/001/034/436/7_tyukijisshikeikaku_r2.pdf","source_pdf_page":46,"source_table_row":5,"claims":[{"field":"policy","value_original":"３－（７）－ウ－② 多様なニーズに対 応する戦略的な販 路拡大と加工・販売 機能の強化"},{"field":"indicator_name","value_original":"沖縄からの農林水産 物・食品の輸出額"},{"field":"baseline","value_original":"40.5億円 （R３年度）"},{"field":"target_r9","value_original":"45.4億円"},{"field":"national_current","value_original":"１兆4,148億円 （R４年度）"}],"review_status":"reviewed"},{"id":"okinawa-midterm-evidence-238","subject_id":"okinawa-midterm-indicator-238","source_url":"https://www.pref.okinawa.jp/_res/projects/default_project/_page_/001/034/436/7_tyukijisshikeikaku_r2.pdf","source_pdf_page":47,"source_table_row":1,"claims":[{"field":"policy","value_original":"３－（７）－ウ－③ 食品産業など他産 業との連携による農 林水産物の付加価 値向上"},{"field":"indicator_name","value_original":"他産業と連携している 農産加工事業者割合"},{"field":"baseline","value_original":"31.6％ （R３年度）"},{"field":"target_r9","value_original":"46.8％"},{"field":"national_current","value_original":"25.8％ （R３年度）"}],"review_status":"reviewed"},{"id":"okinawa-midterm-evidence-239","subject_id":"okinawa-midterm-indicator-239","source_url":"https://www.pref.okinawa.jp/_res/projects/default_project/_page_/001/034/436/7_tyukijisshikeikaku_r2.pdf","source_pdf_page":47,"source_table_row":2,"claims":[{"field":"policy","value_original":"３－（７）－ウ－④ 地産地消等による 県産農林水産物の 消費拡大"},{"field":"indicator_name","value_original":"農水産物直売所の年 間販売額"},{"field":"baseline","value_original":"147億円 （R３年度）"},{"field":"target_r9","value_original":"156億円"},{"field":"national_current","value_original":"1兆1,253億円 （R４年度）"}],"review_status":"reviewed"},{"id":"okinawa-midterm-evidence-240","subject_id":"okinawa-midterm-indicator-240","source_url":"https://www.pref.okinawa.jp/_res/projects/default_project/_page_/001/034/436/7_tyukijisshikeikaku_r2.pdf","source_pdf_page":47,"source_table_row":3,"claims":[{"field":"policy","value_original":"３－（７）－ウ－⑤ 製糖業の経営基盤 強化と高度化推進"},{"field":"indicator_name","value_original":"甘しゃ糖の産糖量"},{"field":"baseline","value_original":"95,072トン （R３年度）"},{"field":"target_r9","value_original":"105,769トン"},{"field":"national_current","value_original":"146,505トン （R４年度）"}],"review_status":"reviewed"},{"id":"okinawa-midterm-evidence-241","subject_id":"okinawa-midterm-indicator-241","source_url":"https://www.pref.okinawa.jp/_res/projects/default_project/_page_/001/034/436/7_tyukijisshikeikaku_r2.pdf","source_pdf_page":47,"source_table_row":4,"claims":[{"field":"policy","value_original":"３－（７）－エ－① 農林水産業の経営 安定対策の充実"},{"field":"indicator_name","value_original":"農業保険（農業共済 及び収入保険）・漁業 共済加入率"},{"field":"baseline","value_original":"水稲 45.8％ さとうきび 43.3％ 園芸施設共済 26.1％ 漁業共済 89.1％ （R３年度）"},{"field":"target_r9","value_original":"水稲 66.4％ さとうきび 47.6％ 園芸施設共済 37.0％ 漁業共済 90.0％"},{"field":"national_current","value_original":"水稲 79.3％ さとうきび 46.1％ 園芸施設共済 77.0％ 漁業共済 87.0％ （R５年度）"}],"review_status":"reviewed"},{"id":"okinawa-midterm-evidence-242","subject_id":"okinawa-midterm-indicator-242","source_url":"https://www.pref.okinawa.jp/_res/projects/default_project/_page_/001/034/436/7_tyukijisshikeikaku_r2.pdf","source_pdf_page":47,"source_table_row":5,"claims":[{"field":"policy","value_original":"３－（７）－エ－② 担い手への農地の 集積・集約化の促進"},{"field":"indicator_name","value_original":"担い手への農地集積 率"},{"field":"baseline","value_original":"25.1％ （R３年度）"},{"field":"target_r9","value_original":"43.6％"},{"field":"national_current","value_original":"58.9％ （R３年度）"}],"review_status":"reviewed"},{"id":"okinawa-midterm-evidence-243","subject_id":"okinawa-midterm-indicator-243","source_url":"https://www.pref.okinawa.jp/_res/projects/default_project/_page_/001/034/436/7_tyukijisshikeikaku_r2.pdf","source_pdf_page":48,"source_table_row":1,"claims":[{"field":"policy","value_original":"３－（７）－エ－③ 農林漁業団体の組 織強化を通じた力強 い経営体づくり"},{"field":"indicator_name","value_original":"認定農業者・認定漁 業者数（累計）"},{"field":"baseline","value_original":"認定農業者数 4,346 人 認定漁業者数 30人 （R３年度）"},{"field":"target_r9","value_original":"認定農業者数 4,897 人 認定漁業者数 36人"},{"field":"national_current","value_original":"認定農業者数 222,374人 認定漁業者数 8,739 人 （R３年度）"}],"review_status":"reviewed"},{"id":"okinawa-midterm-evidence-244","subject_id":"okinawa-midterm-indicator-244","source_url":"https://www.pref.okinawa.jp/_res/projects/default_project/_page_/001/034/436/7_tyukijisshikeikaku_r2.pdf","source_pdf_page":48,"source_table_row":2,"claims":[{"field":"policy","value_original":"３－（７）－オ－① デジタル技術等を活 用したスマート農林 水産技術の実証と 普及"},{"field":"indicator_name","value_original":"スマート農林水産業技 術の導入産地数（累 計）"},{"field":"baseline","value_original":"１産地 （R３年度）"},{"field":"target_r9","value_original":"８産地"},{"field":"national_current","value_original":"4.6産地 （R５年度） （※１県当たりの平 均導入産地数）"}],"review_status":"reviewed"},{"id":"okinawa-midterm-evidence-245","subject_id":"okinawa-midterm-indicator-245","source_url":"https://www.pref.okinawa.jp/_res/projects/default_project/_page_/001/034/436/7_tyukijisshikeikaku_r2.pdf","source_pdf_page":48,"source_table_row":3,"claims":[{"field":"policy","value_original":"３－（７）－オ－② 多様なニーズや気 候変動に対応した 品種の開発と普及"},{"field":"indicator_name","value_original":"新たな品種登録数（累 計）"},{"field":"baseline","value_original":"42品種 （R３年度）"},{"field":"target_r9","value_original":"48品種"},{"field":"national_current","value_original":"7,486品種 （R３年度）"}],"review_status":"reviewed"},{"id":"okinawa-midterm-evidence-246","subject_id":"okinawa-midterm-indicator-246","source_url":"https://www.pref.okinawa.jp/_res/projects/default_project/_page_/001/034/436/7_tyukijisshikeikaku_r2.pdf","source_pdf_page":48,"source_table_row":4,"claims":[{"field":"policy","value_original":"３－（７）－オ－③ 地域特性を最大限 に生かした農林水 産技術の開発と普 及"},{"field":"indicator_name","value_original":"生産現場等への普及 に移す研究成果数（累 計）"},{"field":"baseline","value_original":"614件 （R３年度）"},{"field":"target_r9","value_original":"884件"},{"field":"national_current","value_original":"2,752件 （R３年度） （※国立研究開発法 人の研究成果等の 合計件数）"}],"review_status":"reviewed"},{"id":"okinawa-midterm-evidence-247","subject_id":"okinawa-midterm-indicator-247","source_url":"https://www.pref.okinawa.jp/_res/projects/default_project/_page_/001/034/436/7_tyukijisshikeikaku_r2.pdf","source_pdf_page":48,"source_table_row":5,"claims":[{"field":"policy","value_original":"３－（７）－カ－① 生産性と収益性を 高める農業生産基 盤の整備"},{"field":"indicator_name","value_original":"基盤整備率（かんがい 施設整備率、ほ場整 備率）"},{"field":"baseline","value_original":"51.0％ （かんがい施設整備 率） 64.3％ （ほ場整備率） （R３年度）"},{"field":"target_r9","value_original":"56.4％ （かんがい施設整備 率） 71.0％ （ほ場整備率）"},{"field":"national_current","value_original":"67.0％ （田の用水整備率） 68.0％ （田の30a程度以上 区画整備率） （R３年度）"}],"review_status":"reviewed"},{"id":"okinawa-midterm-evidence-248","subject_id":"okinawa-midterm-indicator-248","source_url":"https://www.pref.okinawa.jp/_res/projects/default_project/_page_/001/034/436/7_tyukijisshikeikaku_r2.pdf","source_pdf_page":49,"source_table_row":1,"claims":[{"field":"policy","value_original":"３－（７）－カ－② 自然環境に配慮し た森林及び林業生 産基盤の整備"},{"field":"indicator_name","value_original":"森林整備面積"},{"field":"baseline","value_original":"526ha （R３年度）"},{"field":"target_r9","value_original":"587㏊"},{"field":"national_current","value_original":"2,220㏊ （R４年度） （※全国の森林整備 事業実績の面積（沖 縄で実施しない作業 を除く）を47（都道府 県）で除した数値）"}],"review_status":"reviewed"},{"id":"okinawa-midterm-evidence-249","subject_id":"okinawa-midterm-indicator-249","source_url":"https://www.pref.okinawa.jp/_res/projects/default_project/_page_/001/034/436/7_tyukijisshikeikaku_r2.pdf","source_pdf_page":49,"source_table_row":2,"claims":[{"field":"policy","value_original":"３－（７）－カ－③ 水産物の生産性を 高める生産基盤の 高度化"},{"field":"indicator_name","value_original":"係留施設の機能高度 化整備率"},{"field":"baseline","value_original":"８％ （R３年度）"},{"field":"target_r9","value_original":"26％"},{"field":"national_current","value_original":"69％（※） （R３年度） （※水産物の流通拠 点や生産拠点となる 漁港において、就労 環境が改善された 漁港の割合）"}],"review_status":"reviewed"},{"id":"okinawa-midterm-evidence-250","subject_id":"okinawa-midterm-indicator-250","source_url":"https://www.pref.okinawa.jp/_res/projects/default_project/_page_/001/034/436/7_tyukijisshikeikaku_r2.pdf","source_pdf_page":49,"source_table_row":3,"claims":[{"field":"policy","value_original":"３－（７）－カ－④ 農山漁村地域の強 靱化対策の推進"},{"field":"indicator_name","value_original":"農業・農村の強靱化 率"},{"field":"baseline","value_original":"13.2％ （R３年度）"},{"field":"target_r9","value_original":"68.4％"},{"field":"national_current","value_original":"46％（※１） 72％（※２） （R４年度） （※１更新等が必要 な基幹的農業水利 施設における対策 着手の割合） （※２防災重点ため 池における防災対 策着手の割合）"}],"review_status":"reviewed"},{"id":"okinawa-midterm-evidence-251","subject_id":"okinawa-midterm-indicator-251","source_url":"https://www.pref.okinawa.jp/_res/projects/default_project/_page_/001/034/436/7_tyukijisshikeikaku_r2.pdf","source_pdf_page":49,"source_table_row":4,"claims":[{"field":"policy","value_original":"３－（７）－キ－① 環境に配慮した持 続可能な農林水産 業の推進"},{"field":"indicator_name","value_original":"環境保全型農業の実 践数（累計）"},{"field":"baseline","value_original":"1,878件 （R３年度）"},{"field":"target_r9","value_original":"2,352件"},{"field":"national_current","value_original":"312,035件 （R元年度） （※全国のエコ ファーマー累積新規 認定件数）"}],"review_status":"reviewed"},{"id":"okinawa-midterm-evidence-252","subject_id":"okinawa-midterm-indicator-252","source_url":"https://www.pref.okinawa.jp/_res/projects/default_project/_page_/001/034/436/7_tyukijisshikeikaku_r2.pdf","source_pdf_page":49,"source_table_row":5,"claims":[{"field":"policy","value_original":"３－（７）－キ－② 地域資源の活用・域 内循環の創出によ る地域の活性化"},{"field":"indicator_name","value_original":"農林水産物の６次産 業化関連事業者の年 間販売額"},{"field":"baseline","value_original":"245億円 （R３年度）"},{"field":"target_r9","value_original":"263億円"},{"field":"national_current","value_original":"２兆2,844億円 （R３年度）"}],"review_status":"reviewed"},{"id":"okinawa-midterm-evidence-253","subject_id":"okinawa-midterm-indicator-253","source_url":"https://www.pref.okinawa.jp/_res/projects/default_project/_page_/001/034/436/7_tyukijisshikeikaku_r2.pdf","source_pdf_page":50,"source_table_row":1,"claims":[{"field":"policy","value_original":"３－（７）－キ－③ 地域が有する多面 的機能の維持・発揮"},{"field":"indicator_name","value_original":"多面的機能の保全が 図られる農用地面積"},{"field":"baseline","value_original":"21,746㏊ （R３年度）"},{"field":"target_r9","value_original":"21,902㏊"},{"field":"national_current","value_original":"2,304,863㏊ （R５年度）"}],"review_status":"reviewed"},{"id":"okinawa-midterm-evidence-254","subject_id":"okinawa-midterm-indicator-254","source_url":"https://www.pref.okinawa.jp/_res/projects/default_project/_page_/001/034/436/7_tyukijisshikeikaku_r2.pdf","source_pdf_page":50,"source_table_row":2,"claims":[{"field":"policy","value_original":"３－（８）－ア－① 域内自給率を高め るものづくり産業の 高度化"},{"field":"indicator_name","value_original":"製造品出荷額"},{"field":"baseline","value_original":"3,766億61百万円 （R３年度）"},{"field":"target_r9","value_original":"5,031億55百万円"},{"field":"national_current","value_original":"279兆3,625億92百 万円 （R３年度）"}],"review_status":"reviewed"},{"id":"okinawa-midterm-evidence-255","subject_id":"okinawa-midterm-indicator-255","source_url":"https://www.pref.okinawa.jp/_res/projects/default_project/_page_/001/034/436/7_tyukijisshikeikaku_r2.pdf","source_pdf_page":50,"source_table_row":3,"claims":[{"field":"policy","value_original":"３－（８）－ア－② ものづくりを支える 基盤・技術の高度化 とサポーティング産 業の振興"},{"field":"indicator_name","value_original":"製造業における付加 価値額"},{"field":"baseline","value_original":"1,656億82百万円 （R３年）"},{"field":"target_r9","value_original":"1,828億34百万円"},{"field":"national_current","value_original":"109兆2,319億46百 万円 （R４年）"}],"review_status":"reviewed"},{"id":"okinawa-midterm-evidence-256","subject_id":"okinawa-midterm-indicator-256","source_url":"https://www.pref.okinawa.jp/_res/projects/default_project/_page_/001/034/436/7_tyukijisshikeikaku_r2.pdf","source_pdf_page":50,"source_table_row":4,"claims":[{"field":"policy","value_original":"３－（８）－イ－① 国内市場における 需要開拓の促進"},{"field":"indicator_name","value_original":"製造品移出額（推計）"},{"field":"baseline","value_original":"628億95百万円 （R３年度）"},{"field":"target_r9","value_original":"840億27百万円"},{"field":"national_current","value_original":"－"}],"review_status":"reviewed"},{"id":"okinawa-midterm-evidence-257","subject_id":"okinawa-midterm-indicator-257","source_url":"https://www.pref.okinawa.jp/_res/projects/default_project/_page_/001/034/436/7_tyukijisshikeikaku_r2.pdf","source_pdf_page":50,"source_table_row":5,"claims":[{"field":"policy","value_original":"３－（８）－イ－② 海外市場における 販路開拓"},{"field":"indicator_name","value_original":"製造品輸出額（推計）"},{"field":"baseline","value_original":"180億78百万円 （R３年度）"},{"field":"target_r9","value_original":"241億51百万円"},{"field":"national_current","value_original":"－"}],"review_status":"reviewed"},{"id":"okinawa-midterm-evidence-258","subject_id":"okinawa-midterm-indicator-258","source_url":"https://www.pref.okinawa.jp/_res/projects/default_project/_page_/001/034/436/7_tyukijisshikeikaku_r2.pdf","source_pdf_page":50,"source_table_row":6,"claims":[{"field":"policy","value_original":"３－（８）－イ－③ 県産品の高付加価 値化の促進"},{"field":"indicator_name","value_original":"名目県内総生産にお ける第１次産業及び 製造業の生産額"},{"field":"baseline","value_original":"2,407億15百万円 （R３年度）"},{"field":"target_r9","value_original":"2,623億65百万円"},{"field":"national_current","value_original":"２兆7,100億1百万円 （R５年） （※47都道府県平均 値）"}],"review_status":"reviewed"},{"id":"okinawa-midterm-evidence-259","subject_id":"okinawa-midterm-indicator-259","source_url":"https://www.pref.okinawa.jp/_res/projects/default_project/_page_/001/034/436/7_tyukijisshikeikaku_r2.pdf","source_pdf_page":51,"source_table_row":1,"claims":[{"field":"policy","value_original":"３－（８）－イ－④ 県産品の消費促進"},{"field":"indicator_name","value_original":"県内で流通される製 造品出荷額"},{"field":"baseline","value_original":"2,960億20百万円 （R３年度）"},{"field":"target_r9","value_original":"3,954億79百万円"},{"field":"national_current","value_original":"－"}],"review_status":"reviewed"},{"id":"okinawa-midterm-evidence-260","subject_id":"okinawa-midterm-indicator-260","source_url":"https://www.pref.okinawa.jp/_res/projects/default_project/_page_/001/034/436/7_tyukijisshikeikaku_r2.pdf","source_pdf_page":51,"source_table_row":2,"claims":[{"field":"policy","value_original":"３－（８）－ウ－① 公共工事の品質確 保と建設産業の高 度化支援"},{"field":"indicator_name","value_original":"建設業における労働 生産性"},{"field":"baseline","value_original":"6,083千円 （R３年度）"},{"field":"target_r9","value_original":"6,287千円 （※全国同等レベ ル）"},{"field":"national_current","value_original":"6,423千円 （R３年度）"}],"review_status":"reviewed"},{"id":"okinawa-midterm-evidence-261","subject_id":"okinawa-midterm-indicator-261","source_url":"https://www.pref.okinawa.jp/_res/projects/default_project/_page_/001/034/436/7_tyukijisshikeikaku_r2.pdf","source_pdf_page":51,"source_table_row":3,"claims":[{"field":"policy","value_original":"３－（８）－ウ－② 地域特性に適した 技術の研究・開発の 促進及び海外建設 市場等への流出"},{"field":"indicator_name","value_original":"海外展開に向けた研 修等に参加した人数 （累計）"},{"field":"baseline","value_original":"18人 （R３年度）"},{"field":"target_r9","value_original":"120人"},{"field":"national_current","value_original":"－"}],"review_status":"reviewed"},{"id":"okinawa-midterm-evidence-262","subject_id":"okinawa-midterm-indicator-262","source_url":"https://www.pref.okinawa.jp/_res/projects/default_project/_page_/001/034/436/7_tyukijisshikeikaku_r2.pdf","source_pdf_page":51,"source_table_row":4,"claims":[{"field":"policy","value_original":"３－（９）－ア－① スポーツコンベン ションの推進とス ポーツ交流拠点の 形成"},{"field":"indicator_name","value_original":"スポーツコンベンショ ン開催実績"},{"field":"baseline","value_original":"347件 （R３年度）"},{"field":"target_r9","value_original":"722件"},{"field":"national_current","value_original":"－"}],"review_status":"reviewed"},{"id":"okinawa-midterm-evidence-263","subject_id":"okinawa-midterm-indicator-263","source_url":"https://www.pref.okinawa.jp/_res/projects/default_project/_page_/001/034/436/7_tyukijisshikeikaku_r2.pdf","source_pdf_page":51,"source_table_row":5,"claims":[{"field":"policy","value_original":"３－（９）－ア－② スポーツを核とした 新たな産業の創出 とグローバル展開"},{"field":"indicator_name","value_original":"沖縄県におけるス ポーツ経済規模（ス ポーツGDP）"},{"field":"baseline","value_original":"1,033億円 （R４年度）"},{"field":"target_r9","value_original":"1,222億円"},{"field":"national_current","value_original":"－"}],"review_status":"reviewed"},{"id":"okinawa-midterm-evidence-264","subject_id":"okinawa-midterm-indicator-264","source_url":"https://www.pref.okinawa.jp/_res/projects/default_project/_page_/001/034/436/7_tyukijisshikeikaku_r2.pdf","source_pdf_page":51,"source_table_row":6,"claims":[{"field":"policy","value_original":"３－（９）－ア－③ スポーツ資源を活用 したまちづくり"},{"field":"indicator_name","value_original":"スポーツコンベンショ ン参加者数（県外、海 外）"},{"field":"baseline","value_original":"17,030人 （R３年度）"},{"field":"target_r9","value_original":"78,144人"},{"field":"national_current","value_original":"－"}],"review_status":"reviewed"},{"id":"okinawa-midterm-evidence-265","subject_id":"okinawa-midterm-indicator-265","source_url":"https://www.pref.okinawa.jp/_res/projects/default_project/_page_/001/034/436/7_tyukijisshikeikaku_r2.pdf","source_pdf_page":52,"source_table_row":1,"claims":[{"field":"policy","value_original":"３－（９）－イ－① スポーツ・レクリエー ション施設及び関連 基盤の整備・充実"},{"field":"indicator_name","value_original":"県立社会体育施設の 利用者数"},{"field":"baseline","value_original":"267,379人 （R３年度）"},{"field":"target_r9","value_original":"684,300人"},{"field":"national_current","value_original":"－"}],"review_status":"reviewed"},{"id":"okinawa-midterm-evidence-266","subject_id":"okinawa-midterm-indicator-266","source_url":"https://www.pref.okinawa.jp/_res/projects/default_project/_page_/001/034/436/7_tyukijisshikeikaku_r2.pdf","source_pdf_page":52,"source_table_row":2,"claims":[{"field":"policy","value_original":"３－（９）－イ－② 県民の競技力向上・ スポーツ活動の推 進"},{"field":"indicator_name","value_original":"県出身日本代表ス ポーツ選手累計（国際 大会）"},{"field":"baseline","value_original":"133名 （R３年度）"},{"field":"target_r9","value_original":"247名"},{"field":"national_current","value_original":"－"}],"review_status":"reviewed"},{"id":"okinawa-midterm-evidence-267","subject_id":"okinawa-midterm-indicator-267","source_url":"https://www.pref.okinawa.jp/_res/projects/default_project/_page_/001/034/436/7_tyukijisshikeikaku_r2.pdf","source_pdf_page":52,"source_table_row":3,"claims":[{"field":"policy","value_original":"３－（９）－イ－③ 県民一人ひとりが参 加する生涯スポーツ の推進"},{"field":"indicator_name","value_original":"スポーツ実施率"},{"field":"baseline","value_original":"58.3％ （R３年度）"},{"field":"target_r9","value_original":"66.3%"},{"field":"national_current","value_original":"53.6％ （R元年度）"}],"review_status":"reviewed"},{"id":"okinawa-midterm-evidence-268","subject_id":"okinawa-midterm-indicator-268","source_url":"https://www.pref.okinawa.jp/_res/projects/default_project/_page_/001/034/436/7_tyukijisshikeikaku_r2.pdf","source_pdf_page":52,"source_table_row":4,"claims":[{"field":"policy","value_original":"３－（１０）－アー① 離島におけるさとう きび産業の振興"},{"field":"indicator_name","value_original":"さとうきびの生産量 （離島）"},{"field":"baseline","value_original":"693,604トン （R３年度）"},{"field":"target_r9","value_original":"712,000トン"},{"field":"national_current","value_original":"1,270,550トン （R４年度）"}],"review_status":"reviewed"},{"id":"okinawa-midterm-evidence-269","subject_id":"okinawa-midterm-indicator-269","source_url":"https://www.pref.okinawa.jp/_res/projects/default_project/_page_/001/034/436/7_tyukijisshikeikaku_r2.pdf","source_pdf_page":52,"source_table_row":5,"claims":[{"field":"policy","value_original":"３－（１０）－アー② 離島における畜産 業の振興"},{"field":"indicator_name","value_original":"肉用子牛の取引頭数 （離島）"},{"field":"baseline","value_original":"17,405頭 （R３年度）"},{"field":"target_r9","value_original":"19,248頭"},{"field":"national_current","value_original":"43,373頭 （R３年度）"}],"review_status":"reviewed"},{"id":"okinawa-midterm-evidence-270","subject_id":"okinawa-midterm-indicator-270","source_url":"https://www.pref.okinawa.jp/_res/projects/default_project/_page_/001/034/436/7_tyukijisshikeikaku_r2.pdf","source_pdf_page":52,"source_table_row":6,"claims":[{"field":"policy","value_original":"３－（１０）－アー③ 離島農林水産物の 生産振興とブランド 化の推進"},{"field":"indicator_name","value_original":"離島市町村の農業産 出額（推計）"},{"field":"baseline","value_original":"419.5億円 （R３年）"},{"field":"target_r9","value_original":"501.9億円"},{"field":"national_current","value_original":"1,918億円 （R４年） （※全国の農業産出 額を都道府県数47 で除した平均値）"}],"review_status":"reviewed"},{"id":"okinawa-midterm-evidence-271","subject_id":"okinawa-midterm-indicator-271","source_url":"https://www.pref.okinawa.jp/_res/projects/default_project/_page_/001/034/436/7_tyukijisshikeikaku_r2.pdf","source_pdf_page":53,"source_table_row":1,"claims":[{"field":"policy","value_original":"３－（１０）－アー④ 離島における水産 業の振興"},{"field":"indicator_name","value_original":"漁業生産量（離島推 計）"},{"field":"baseline","value_original":"15,474トン （R３年度）"},{"field":"target_r9","value_original":"11,270トン"},{"field":"national_current","value_original":"－"}],"review_status":"reviewed"},{"id":"okinawa-midterm-evidence-272","subject_id":"okinawa-midterm-indicator-272","source_url":"https://www.pref.okinawa.jp/_res/projects/default_project/_page_/001/034/436/7_tyukijisshikeikaku_r2.pdf","source_pdf_page":53,"source_table_row":2,"claims":[{"field":"policy","value_original":"３－（１０）－アー⑤ 亜熱帯・島しょ性に 適合した農林水産 業の基盤整備"},{"field":"indicator_name","value_original":"かんがい施設整備率 （離島）"},{"field":"baseline","value_original":"58.5％ （R３年度）"},{"field":"target_r9","value_original":"63.7％"},{"field":"national_current","value_original":"67.0％ （R３年度） （※全国の田の用水 整備率）"}],"review_status":"reviewed"},{"id":"okinawa-midterm-evidence-273","subject_id":"okinawa-midterm-indicator-273","source_url":"https://www.pref.okinawa.jp/_res/projects/default_project/_page_/001/034/436/7_tyukijisshikeikaku_r2.pdf","source_pdf_page":53,"source_table_row":3,"claims":[{"field":"policy","value_original":"３－（１０）－イー① 個性的で魅力のあ る特産品開発支援"},{"field":"indicator_name","value_original":"工芸品生産額（離島）"},{"field":"baseline","value_original":"6.7億円 （R３年度）"},{"field":"target_r9","value_original":"10.2億円"},{"field":"national_current","value_original":"－"}],"review_status":"reviewed"},{"id":"okinawa-midterm-evidence-274","subject_id":"okinawa-midterm-indicator-274","source_url":"https://www.pref.okinawa.jp/_res/projects/default_project/_page_/001/034/436/7_tyukijisshikeikaku_r2.pdf","source_pdf_page":53,"source_table_row":4,"claims":[{"field":"policy","value_original":"３－（１０）－イー② 特産品の販路拡大・ プロモーション支援"},{"field":"indicator_name","value_original":"離島フェア売上総額"},{"field":"baseline","value_original":"3,111万円 （R３年度）"},{"field":"target_r9","value_original":"9,000万円"},{"field":"national_current","value_original":"－"}],"review_status":"reviewed"},{"id":"okinawa-midterm-evidence-275","subject_id":"okinawa-midterm-indicator-275","source_url":"https://www.pref.okinawa.jp/_res/projects/default_project/_page_/001/034/436/7_tyukijisshikeikaku_r2.pdf","source_pdf_page":53,"source_table_row":5,"claims":[{"field":"policy","value_original":"３－（１０）－ウー① 着地型観光プログラ ム等の定着"},{"field":"indicator_name","value_original":"離島地域（宮古圏域、 八重山圏域、久米島 圏域）の一人当たり観 光消費額"},{"field":"baseline","value_original":"八重山 96,412円 宮古 101,550円 久米島 59,972円 （R３年度）"},{"field":"target_r9","value_original":"八重山 104,600円 宮古 104,171円 久米島 75,401円"},{"field":"national_current","value_original":"－"}],"review_status":"reviewed"},{"id":"okinawa-midterm-evidence-276","subject_id":"okinawa-midterm-indicator-276","source_url":"https://www.pref.okinawa.jp/_res/projects/default_project/_page_/001/034/436/7_tyukijisshikeikaku_r2.pdf","source_pdf_page":54,"source_table_row":1,"claims":[{"field":"policy","value_original":"３－（１０）－ウー② 環境に配慮した持 続可能な観光の推 進"},{"field":"indicator_name","value_original":"離島の持続可能な観 光を推進するための 取組が行われている と感じた観光客の割 合"},{"field":"baseline","value_original":"宮古 37.1％ 八重山 45.4％ 久米島 31.1％ （R３年度）"},{"field":"target_r9","value_original":"宮古 60.0％ 八重山 60.0％ 久米島 60.0％"},{"field":"national_current","value_original":"－"}],"review_status":"reviewed"},{"id":"okinawa-midterm-evidence-277","subject_id":"okinawa-midterm-indicator-277","source_url":"https://www.pref.okinawa.jp/_res/projects/default_project/_page_/001/034/436/7_tyukijisshikeikaku_r2.pdf","source_pdf_page":54,"source_table_row":2,"claims":[{"field":"policy","value_original":"３－（１１）－ア－① 総合的な就業支援"},{"field":"indicator_name","value_original":"就業率（年平均値）"},{"field":"baseline","value_original":"60.0％ （R３年）"},{"field":"target_r9","value_original":"61.5%"},{"field":"national_current","value_original":"61.2％ （R５年）"}],"review_status":"reviewed"},{"id":"okinawa-midterm-evidence-278","subject_id":"okinawa-midterm-indicator-278","source_url":"https://www.pref.okinawa.jp/_res/projects/default_project/_page_/001/034/436/7_tyukijisshikeikaku_r2.pdf","source_pdf_page":54,"source_table_row":3,"claims":[{"field":"policy","value_original":"３－（１１）－ア－② 高齢者が活躍でき る環境づくり"},{"field":"indicator_name","value_original":"65歳以上就業率（年 平均値）"},{"field":"baseline","value_original":"23.1％ （R３年）"},{"field":"target_r9","value_original":"25.1%"},{"field":"national_current","value_original":"25.2％ （R４年）"}],"review_status":"reviewed"},{"id":"okinawa-midterm-evidence-279","subject_id":"okinawa-midterm-indicator-279","source_url":"https://www.pref.okinawa.jp/_res/projects/default_project/_page_/001/034/436/7_tyukijisshikeikaku_r2.pdf","source_pdf_page":54,"source_table_row":4,"claims":[{"field":"policy","value_original":"３－（１１）－ア－③ 障害者の雇用の場 の創出と働きやすい 環境づくり"},{"field":"indicator_name","value_original":"障害者実雇用率"},{"field":"baseline","value_original":"2.86％ （R３年）"},{"field":"target_r9","value_original":"3.68%"},{"field":"national_current","value_original":"2.33% （R5年）"}],"review_status":"reviewed"},{"id":"okinawa-midterm-evidence-280","subject_id":"okinawa-midterm-indicator-280","source_url":"https://www.pref.okinawa.jp/_res/projects/default_project/_page_/001/034/436/7_tyukijisshikeikaku_r2.pdf","source_pdf_page":54,"source_table_row":5,"claims":[{"field":"policy","value_original":"３－（１１）－ア－④ 外国人材の受入環 境の整備"},{"field":"indicator_name","value_original":"外国人労働者数"},{"field":"baseline","value_original":"10,498人 （R３年）"},{"field":"target_r9","value_original":"16,200人"},{"field":"national_current","value_original":"2,048,675人 （R５年）"}],"review_status":"reviewed"},{"id":"okinawa-midterm-evidence-281","subject_id":"okinawa-midterm-indicator-281","source_url":"https://www.pref.okinawa.jp/_res/projects/default_project/_page_/001/034/436/7_tyukijisshikeikaku_r2.pdf","source_pdf_page":54,"source_table_row":6,"claims":[{"field":"policy","value_original":"３－（１１）－ア－⑤ 駐留軍等労働者の 雇用対策の推進"},{"field":"indicator_name","value_original":"駐留軍用地の返還に 伴い離職を余儀なくさ れる駐留軍等従業員 の再就職率"},{"field":"baseline","value_original":"-"},{"field":"target_r9","value_original":"求職者のうち、３年 以内に再就職した 人の割合 100％"},{"field":"national_current","value_original":"－"}],"review_status":"reviewed"},{"id":"okinawa-midterm-evidence-282","subject_id":"okinawa-midterm-indicator-282","source_url":"https://www.pref.okinawa.jp/_res/projects/default_project/_page_/001/034/436/7_tyukijisshikeikaku_r2.pdf","source_pdf_page":55,"source_table_row":1,"claims":[{"field":"policy","value_original":"３－（１１）－イ－① 柔軟な働き方の推 進のための環境整 備"},{"field":"indicator_name","value_original":"テレワーク実施率"},{"field":"baseline","value_original":"22.2％ （R３年度）"},{"field":"target_r9","value_original":"32.0%"},{"field":"national_current","value_original":"51.9％ （R３年度）"}],"review_status":"reviewed"}],"updated_at":"2026-07-22"}