{"id":"miyagi-kpi-actuals-measure7-2024","municipality_key":"miyagi-prefecture","source_id":"policy-source-miyagi-results-evaluation-2025","source_document_url":"https://www.pref.miyagi.jp/documents/59769/r7-seikatohyouka_1.pdf","evaluation_fiscal_year":2025,"subject_fiscal_year":2024,"measure_number":7,"records":[{"id":"miyagi-kpi-actual-link-50","target_group_id":"policy-target-miyagi-46","series_id":"policy-indicator-miyagi-50","linkage_status":"linked","match_basis":"exact_name_and_unit","source_indicator_number":43,"source_indicator_name_original":"県内における子ども食堂の数（箇所）［累計］","source_pdf_page":82,"achievement_rate_type_original":"進捗割合型Ⅰ","evaluation_baseline":{"period_original":"R2","period_year":2020,"value":70,"value_text_original":"70","unit_original":"箇所"},"evaluation_target":{"period_original":"R6","period_year":2024,"value":180,"value_text_original":"180","unit_original":"箇所"},"annual_results":[{"reporting_period_original":"R3","reporting_year":2021,"measurement_period_original":"R3","measurement_year":2021,"value":103,"value_text_original":"103","unit_original":"箇所","achievement_rate_text_original":"30.0%","achievement_rate_value":30.0,"achievement_rate_status":"numeric","achievement_grade":"not_set"},{"reporting_period_original":"R4","reporting_year":2022,"measurement_period_original":"R4","measurement_year":2022,"value":139,"value_text_original":"139","unit_original":"箇所","achievement_rate_text_original":"62.7%","achievement_rate_value":62.7,"achievement_rate_status":"numeric","achievement_grade":"A"},{"reporting_period_original":"R5","reporting_year":2023,"measurement_period_original":"R5","measurement_year":2023,"value":154,"value_text_original":"154","unit_original":"箇所","achievement_rate_text_original":"76.4%","achievement_rate_value":76.4,"achievement_rate_status":"numeric","achievement_grade":"A"},{"reporting_period_original":"R6","reporting_year":2024,"measurement_period_original":"R6","measurement_year":2024,"value":198,"value_text_original":"198","unit_original":"箇所","achievement_rate_text_original":"100%超","achievement_rate_value":null,"achievement_rate_status":"above_100","achievement_grade":"A"}],"comparability_note_original":"公式達成率は評価書の令和6年度目標180箇所を基準とする。現行中期実施計画の令和9年度目標260箇所に対する達成率として流用しない。累計値を単年度開設数へ変換しない。","review_status":"reviewed","confidence":"high"},{"id":"miyagi-kpi-actual-link-51","target_group_id":"policy-target-miyagi-47","series_id":"policy-indicator-miyagi-51","linkage_status":"linked","match_basis":"exact_name_and_unit","source_indicator_number":44,"source_indicator_name_original":"里親委託率（%）","source_pdf_page":83,"achievement_rate_type_original":"進捗割合型Ⅰ","evaluation_baseline":{"period_original":"R1","period_year":2019,"value":37.6,"value_text_original":"37.6","unit_original":"%"},"evaluation_target":{"period_original":"R6","period_year":2024,"value":51.4,"value_text_original":"51.4","unit_original":"%"},"annual_results":[{"reporting_period_original":"R3","reporting_year":2021,"measurement_period_original":"R3","measurement_year":2021,"value":40.7,"value_text_original":"40.7","unit_original":"%","achievement_rate_text_original":"19.5%","achievement_rate_value":19.5,"achievement_rate_status":"numeric","achievement_grade":"not_set"},{"reporting_period_original":"R4","reporting_year":2022,"measurement_period_original":"R4","measurement_year":2022,"value":32.8,"value_text_original":"32.8","unit_original":"%","achievement_rate_text_original":"0%未満","achievement_rate_value":null,"achievement_rate_status":"below_0","achievement_grade":"D"},{"reporting_period_original":"R5","reporting_year":2023,"measurement_period_original":"R5","measurement_year":2023,"value":34.7,"value_text_original":"34.7","unit_original":"%","achievement_rate_text_original":"0%未満","achievement_rate_value":null,"achievement_rate_status":"below_0","achievement_grade":"D"},{"reporting_period_original":"R6","reporting_year":2024,"measurement_period_original":"R6","measurement_year":2024,"value":36.7,"value_text_original":"36.7","unit_original":"%","achievement_rate_text_original":"0%未満","achievement_rate_value":null,"achievement_rate_status":"below_0","achievement_grade":"D"}],"comparability_note_original":"公式達成率は評価書の令和6年度目標51.4%を基準とし、現行中期実施計画の令和9年度目標57.5%とは分離する。","review_status":"reviewed","confidence":"high"},{"id":"miyagi-kpi-actual-link-52","target_group_id":"policy-target-miyagi-48","series_id":"policy-indicator-miyagi-52","linkage_status":"linked","match_basis":"exact_name_and_unit","source_indicator_number":45,"source_indicator_name_original":"朝食を毎日食べる児童の割合（小学6年生）（%）","source_pdf_page":83,"achievement_rate_type_original":"進捗割合型Ⅰ","evaluation_baseline":{"period_original":"R1","period_year":2019,"value":96.5,"value_text_original":"96.5","unit_original":"%"},"evaluation_target":{"period_original":"R6","period_year":2024,"value":97.0,"value_text_original":"97.0","unit_original":"%"},"annual_results":[{"reporting_period_original":"R3","reporting_year":2021,"measurement_period_original":"R3","measurement_year":2021,"value":95.3,"value_text_original":"95.3","unit_original":"%","achievement_rate_text_original":"0%未満","achievement_rate_value":null,"achievement_rate_status":"below_0","achievement_grade":"not_set"},{"reporting_period_original":"R4","reporting_year":2022,"measurement_period_original":"R4","measurement_year":2022,"value":94.2,"value_text_original":"94.2","unit_original":"%","achievement_rate_text_original":"0%未満","achievement_rate_value":null,"achievement_rate_status":"below_0","achievement_grade":"D"},{"reporting_period_original":"R5","reporting_year":2023,"measurement_period_original":"R5","measurement_year":2023,"value":93.9,"value_text_original":"93.9","unit_original":"%","achievement_rate_text_original":"0%未満","achievement_rate_value":null,"achievement_rate_status":"below_0","achievement_grade":"D"},{"reporting_period_original":"R6","reporting_year":2024,"measurement_period_original":"R6","measurement_year":2024,"value":93.1,"value_text_original":"93.1","unit_original":"%","achievement_rate_text_original":"0%未満","achievement_rate_value":null,"achievement_rate_status":"below_0","achievement_grade":"D"}],"comparability_note_original":"評価書の令和6年度実績は93.1%だが、現行中期実施計画の初期値は同じ令和6年について94.2%である。資料間の調査時点又は改定差分を保持し、自動上書きしない。","review_status":"reviewed","confidence":"medium"},{"id":"miyagi-kpi-actual-link-55","target_group_id":"policy-target-miyagi-50","series_id":"policy-indicator-miyagi-55","linkage_status":"needs_review","match_basis":"definition_changed","source_indicator_number":46,"source_indicator_name_original":"市町村における子育てサポーター及び子育てサポーターリーダーの活動者数（人）","source_pdf_page":83,"achievement_rate_type_original":"現状維持型Ⅰ","evaluation_baseline":{"period_original":"R1","period_year":2019,"value":300,"value_text_original":"300","unit_original":"人"},"evaluation_target":{"period_original":"R6","period_year":2024,"value":300,"value_text_original":"300","unit_original":"人"},"annual_results":[{"reporting_period_original":"R3","reporting_year":2021,"measurement_period_original":"R3","measurement_year":2021,"value":410,"value_text_original":"410","unit_original":"人","achievement_rate_text_original":"100%超","achievement_rate_value":null,"achievement_rate_status":"above_100","achievement_grade":"not_set"},{"reporting_period_original":"R4","reporting_year":2022,"measurement_period_original":"R4","measurement_year":2022,"value":404,"value_text_original":"404","unit_original":"人","achievement_rate_text_original":"100%超","achievement_rate_value":null,"achievement_rate_status":"above_100","achievement_grade":"A"},{"reporting_period_original":"R5","reporting_year":2023,"measurement_period_original":"R5","measurement_year":2023,"value":417,"value_text_original":"417","unit_original":"人","achievement_rate_text_original":"100%超","achievement_rate_value":null,"achievement_rate_status":"above_100","achievement_grade":"A"},{"reporting_period_original":"R6","reporting_year":2024,"measurement_period_original":"R6","measurement_year":2024,"value":398,"value_text_original":"398","unit_original":"人","achievement_rate_text_original":"100%超","achievement_rate_value":null,"achievement_rate_status":"above_100","achievement_grade":"A"}],"comparability_note_original":"現行系列55は家庭教育支援チームで活動する支援者数であり、旧評価指標は子育てサポーター及びリーダーの活動者数である。対象資格・所属範囲の一致を確認するまで同一系列として接続しない。","review_status":"reviewed","confidence":"medium"},{"id":"miyagi-kpi-actual-link-56","target_group_id":"policy-target-miyagi-51","series_id":"policy-indicator-miyagi-56","linkage_status":"linked","match_basis":"exact_name_and_unit","source_indicator_number":47,"source_indicator_name_original":"「家庭教育支援チーム」の活動件数（件）","source_pdf_page":83,"achievement_rate_type_original":"進捗割合型Ⅰ","evaluation_baseline":{"period_original":"R1","period_year":2019,"value":79,"value_text_original":"79","unit_original":"件"},"evaluation_target":{"period_original":"R6","period_year":2024,"value":101,"value_text_original":"101","unit_original":"件"},"annual_results":[{"reporting_period_original":"R3","reporting_year":2021,"measurement_period_original":"R3","measurement_year":2021,"value":210,"value_text_original":"210","unit_original":"件","achievement_rate_text_original":"100%超","achievement_rate_value":null,"achievement_rate_status":"above_100","achievement_grade":"not_set"},{"reporting_period_original":"R4","reporting_year":2022,"measurement_period_original":"R4","measurement_year":2022,"value":268,"value_text_original":"268","unit_original":"件","achievement_rate_text_original":"100%超","achievement_rate_value":null,"achievement_rate_status":"above_100","achievement_grade":"A"},{"reporting_period_original":"R5","reporting_year":2023,"measurement_period_original":"R5","measurement_year":2023,"value":314,"value_text_original":"314","unit_original":"件","achievement_rate_text_original":"100%超","achievement_rate_value":null,"achievement_rate_status":"above_100","achievement_grade":"A"},{"reporting_period_original":"R6","reporting_year":2024,"measurement_period_original":"R6","measurement_year":2024,"value":373,"value_text_original":"373","unit_original":"件","achievement_rate_text_original":"100%超","achievement_rate_value":null,"achievement_rate_status":"above_100","achievement_grade":"A"}],"comparability_note_original":"公式達成率は評価書の令和6年度目標101件を基準とする。現行中期実施計画の令和9年度目標350件に対する達成率として流用しない。","review_status":"reviewed","confidence":"high"},{"id":"miyagi-kpi-actual-link-57","target_group_id":"policy-target-miyagi-52","series_id":"policy-indicator-miyagi-57","linkage_status":"linked","match_basis":"exact_name_and_unit","source_indicator_number":48,"source_indicator_name_original":"地域学校協働本部がカバーする学校の割合（公立小・中学校）（仙台市を除く）（%）","source_pdf_page":84,"achievement_rate_type_original":"進捗割合型Ⅰ","evaluation_baseline":{"period_original":"R1","period_year":2019,"value":54.3,"value_text_original":"54.3","unit_original":"%"},"evaluation_target":{"period_original":"R6","period_year":2024,"value":70.0,"value_text_original":"70.0","unit_original":"%"},"annual_results":[{"reporting_period_original":"R3","reporting_year":2021,"measurement_period_original":"R2","measurement_year":2020,"value":63.9,"value_text_original":"63.9","unit_original":"%","achievement_rate_text_original":"61.1%","achievement_rate_value":61.1,"achievement_rate_status":"numeric","achievement_grade":"not_set"},{"reporting_period_original":"R4","reporting_year":2022,"measurement_period_original":"R4","measurement_year":2022,"value":67.4,"value_text_original":"67.4","unit_original":"%","achievement_rate_text_original":"83.4%","achievement_rate_value":83.4,"achievement_rate_status":"numeric","achievement_grade":"A"},{"reporting_period_original":"R5","reporting_year":2023,"measurement_period_original":"R5","measurement_year":2023,"value":74.6,"value_text_original":"74.6","unit_original":"%","achievement_rate_text_original":"100%超","achievement_rate_value":null,"achievement_rate_status":"above_100","achievement_grade":"A"},{"reporting_period_original":"R6","reporting_year":2024,"measurement_period_original":"R6","measurement_year":2024,"value":80.0,"value_text_original":"80.0","unit_original":"%","achievement_rate_text_original":"100%超","achievement_rate_value":null,"achievement_rate_status":"above_100","achievement_grade":"A"}],"comparability_note_original":"令和3年度欄の実績63.9%は測定年度令和2年度である。報告年度と測定年度を分離し、現行計画の令和9年度目標85.0%とは別に保持する。","review_status":"reviewed","confidence":"high"}],"reviewed_at":"2026-07-20","review_status":"reviewed","confidence":"high"}