{"id":"miyagi-kpi-actuals-measure11-2024","municipality_key":"miyagi-prefecture","source_id":"policy-source-miyagi-results-evaluation-2025","source_document_url":"https://www.pref.miyagi.jp/documents/59769/r7-seikatohyouka_1.pdf","evaluation_fiscal_year":2025,"subject_fiscal_year":2024,"measure_number":11,"records":[{"id":"miyagi-kpi-actual-link-99","target_group_id":"policy-target-miyagi-81","series_id":"policy-indicator-miyagi-99","linkage_status":"linked","match_basis":"exact_name_and_unit","source_indicator_number":86,"source_indicator_name_original":"みやぎ県民文化創造の祭典参加者の意識の変化（文化芸術が身近な所で様々な分野に活用され地域の活性化に役立っていると思う人の割合）（%）","source_pdf_page":120,"achievement_rate_type_original":"進捗割合型Ⅰ","evaluation_baseline":{"period_original":"R2","period_year":2020,"value":27.5,"value_text_original":"27.5","unit_original":"%"},"evaluation_target":{"period_original":"R6","period_year":2024,"value":60.0,"value_text_original":"60.0","unit_original":"%"},"annual_results":[{"reporting_period_original":"R3","reporting_year":2021,"measurement_period_original":"R3","measurement_year":2021,"value":85.0,"value_text_original":"85.0","unit_original":"%","achievement_rate_text_original":"100%超","achievement_rate_value":null,"achievement_rate_status":"above_100","achievement_grade":"not_set"},{"reporting_period_original":"R4","reporting_year":2022,"measurement_period_original":"R4","measurement_year":2022,"value":73.3,"value_text_original":"73.3","unit_original":"%","achievement_rate_text_original":"100%超","achievement_rate_value":null,"achievement_rate_status":"above_100","achievement_grade":"A"},{"reporting_period_original":"R5","reporting_year":2023,"measurement_period_original":"R5","measurement_year":2023,"value":77.3,"value_text_original":"77.3","unit_original":"%","achievement_rate_text_original":"100%超","achievement_rate_value":null,"achievement_rate_status":"above_100","achievement_grade":"A"},{"reporting_period_original":"R6","reporting_year":2024,"measurement_period_original":"R6","measurement_year":2024,"value":76.5,"value_text_original":"76.5","unit_original":"%","achievement_rate_text_original":"100%超","achievement_rate_value":null,"achievement_rate_status":"above_100","achievement_grade":"A"}],"comparability_note_original":"名称・単位が一致する。令和5年度77.3%と令和6年度76.5%は現行計画の初期値・現況値と一致する。評価書の令和6年度目標60.0%と現行計画の令和9年度目標79.1%は分離する。","review_status":"reviewed","confidence":"high"},{"id":"miyagi-kpi-actual-link-100","target_group_id":"policy-target-miyagi-81","series_id":"policy-indicator-miyagi-100","linkage_status":"linked","match_basis":"exact_name_and_unit","source_indicator_number":87,"source_indicator_name_original":"みやぎ県民文化創造の祭典参加者の意識の変化（不安を抱える方々の心のケアのために文化芸術の果たす役割が大切だと思う人の割合）（%）","source_pdf_page":121,"achievement_rate_type_original":"進捗割合型Ⅰ","evaluation_baseline":{"period_original":"R2","period_year":2020,"value":66.5,"value_text_original":"66.5","unit_original":"%"},"evaluation_target":{"period_original":"R6","period_year":2024,"value":80.0,"value_text_original":"80.0","unit_original":"%"},"annual_results":[{"reporting_period_original":"R3","reporting_year":2021,"measurement_period_original":"R3","measurement_year":2021,"value":92.7,"value_text_original":"92.7","unit_original":"%","achievement_rate_text_original":"100%超","achievement_rate_value":null,"achievement_rate_status":"above_100","achievement_grade":"not_set"},{"reporting_period_original":"R4","reporting_year":2022,"measurement_period_original":"R4","measurement_year":2022,"value":82.2,"value_text_original":"82.2","unit_original":"%","achievement_rate_text_original":"100%超","achievement_rate_value":null,"achievement_rate_status":"above_100","achievement_grade":"A"},{"reporting_period_original":"R5","reporting_year":2023,"measurement_period_original":"R5","measurement_year":2023,"value":81.4,"value_text_original":"81.4","unit_original":"%","achievement_rate_text_original":"100%超","achievement_rate_value":null,"achievement_rate_status":"above_100","achievement_grade":"A"},{"reporting_period_original":"R6","reporting_year":2024,"measurement_period_original":"R6","measurement_year":2024,"value":82.5,"value_text_original":"82.5","unit_original":"%","achievement_rate_text_original":"100%超","achievement_rate_value":null,"achievement_rate_status":"above_100","achievement_grade":"A"}],"comparability_note_original":"名称・単位が一致する。令和5年度81.4%と令和6年度82.5%は現行計画の初期値・現況値と一致する。評価書の令和6年度目標80.0%と現行計画の令和9年度目標82.6%は分離する。","review_status":"reviewed","confidence":"high"},{"id":"miyagi-kpi-actual-link-101","target_group_id":"policy-target-miyagi-82","series_id":"policy-indicator-miyagi-101","linkage_status":"linked","match_basis":"exact_name_and_unit","source_indicator_number":88,"source_indicator_name_original":"総合型地域スポーツクラブの市町村における育成率（%）","source_pdf_page":121,"achievement_rate_type_original":"進捗割合型Ⅰ","evaluation_baseline":{"period_original":"R2","period_year":2020,"value":77.1,"value_text_original":"77.1","unit_original":"%"},"evaluation_target":{"period_original":"R6","period_year":2024,"value":100.0,"value_text_original":"100.0","unit_original":"%"},"annual_results":[{"reporting_period_original":"R3","reporting_year":2021,"measurement_period_original":"R3","measurement_year":2021,"value":77.1,"value_text_original":"77.1","unit_original":"%","achievement_rate_text_original":"0.0%","achievement_rate_value":0.0,"achievement_rate_status":"numeric","achievement_grade":"not_set"},{"reporting_period_original":"R4","reporting_year":2022,"measurement_period_original":"R4","measurement_year":2022,"value":77.1,"value_text_original":"77.1","unit_original":"%","achievement_rate_text_original":"0.0%","achievement_rate_value":0.0,"achievement_rate_status":"numeric","achievement_grade":"D"},{"reporting_period_original":"R5","reporting_year":2023,"measurement_period_original":"R5","measurement_year":2023,"value":77.1,"value_text_original":"77.1","unit_original":"%","achievement_rate_text_original":"0.0%","achievement_rate_value":0.0,"achievement_rate_status":"numeric","achievement_grade":"D"},{"reporting_period_original":"R6","reporting_year":2024,"measurement_period_original":"R6","measurement_year":2024,"value":80.0,"value_text_original":"80.0","unit_original":"%","achievement_rate_text_original":"12.7%","achievement_rate_value":12.7,"achievement_rate_status":"numeric","achievement_grade":"D"}],"comparability_note_original":"名称・単位が一致する。評価書の令和6年度実績80.0%は現行計画の同年度初期値・現況値と一致する。公式達成率は評価書の令和6年度目標100.0%を基準とする。","review_status":"reviewed","confidence":"high"},{"id":"miyagi-kpi-actual-link-102","target_group_id":"policy-target-miyagi-83","series_id":"policy-indicator-miyagi-102","linkage_status":"needs_review","match_basis":"definition_changed","source_indicator_number":89,"source_indicator_name_original":"生涯学習プラットフォーム閲覧数（セッション数）（件）","source_pdf_page":121,"achievement_rate_type_original":"進捗割合型Ⅰ","evaluation_baseline":{"period_original":"R2","period_year":2020,"value":0,"value_text_original":"0","unit_original":"件"},"evaluation_target":{"period_original":"R6","period_year":2024,"value":48000,"value_text_original":"48,000","unit_original":"件"},"annual_results":[{"reporting_period_original":"R3","reporting_year":2021,"measurement_period_original":"R3","measurement_year":2021,"value":5488,"value_text_original":"5,488","unit_original":"件","achievement_rate_text_original":"11.4%","achievement_rate_value":11.4,"achievement_rate_status":"numeric","achievement_grade":"not_set"},{"reporting_period_original":"R4","reporting_year":2022,"measurement_period_original":"R4","measurement_year":2022,"value":14045,"value_text_original":"14,045","unit_original":"件","achievement_rate_text_original":"29.3%","achievement_rate_value":29.3,"achievement_rate_status":"numeric","achievement_grade":"D"},{"reporting_period_original":"R5","reporting_year":2023,"measurement_period_original":"R5","measurement_year":2023,"value":22712,"value_text_original":"22,712","unit_original":"件","achievement_rate_text_original":"47.3%","achievement_rate_value":47.3,"achievement_rate_status":"numeric","achievement_grade":"C"},{"reporting_period_original":"R6","reporting_year":2024,"measurement_period_original":"R6","measurement_year":2024,"value":19555,"value_text_original":"19,555","unit_original":"件","achievement_rate_text_original":"40.7%","achievement_rate_value":40.7,"achievement_rate_status":"numeric","achievement_grade":"D"}],"comparability_note_original":"旧評価指標はセッション数、現行系列102は「まなびのWEB宮城」のページビュー数である。令和5年度値も22,712件対55,831件で異なるため直接接続しない。","review_status":"reviewed","confidence":"medium"},{"id":"miyagi-kpi-actual-link-103","target_group_id":"policy-target-miyagi-84","series_id":"policy-indicator-miyagi-103","linkage_status":"linked","match_basis":"exact_name_and_unit","source_indicator_number":90,"source_indicator_name_original":"市町村社会教育講座の参加者数（人口千人当たり）（人）","source_pdf_page":121,"achievement_rate_type_original":"進捗割合型Ⅰ","evaluation_baseline":{"period_original":"H30","period_year":2018,"value":744,"value_text_original":"744","unit_original":"人"},"evaluation_target":{"period_original":"R6","period_year":2024,"value":756,"value_text_original":"756","unit_original":"人"},"annual_results":[{"reporting_period_original":"R3","reporting_year":2021,"measurement_period_original":"R2","measurement_year":2020,"value":191,"value_text_original":"191","unit_original":"人","achievement_rate_text_original":"0%未満","achievement_rate_value":null,"achievement_rate_status":"below_0","achievement_grade":"not_set"},{"reporting_period_original":"R4","reporting_year":2022,"measurement_period_original":"R3","measurement_year":2021,"value":320,"value_text_original":"320","unit_original":"人","achievement_rate_text_original":"0%未満","achievement_rate_value":null,"achievement_rate_status":"below_0","achievement_grade":"D"},{"reporting_period_original":"R5","reporting_year":2023,"measurement_period_original":"R4","measurement_year":2022,"value":373,"value_text_original":"373","unit_original":"人","achievement_rate_text_original":"0%未満","achievement_rate_value":null,"achievement_rate_status":"below_0","achievement_grade":"D"},{"reporting_period_original":"R6","reporting_year":2024,"measurement_period_original":"R5","measurement_year":2023,"value":545,"value_text_original":"545","unit_original":"人","achievement_rate_text_original":"0%未満","achievement_rate_value":null,"achievement_rate_status":"below_0","achievement_grade":"D"}],"comparability_note_original":"名称・人口千人当たりの範囲・単位が一致する。評価書は報告年度の前年を測定年度としており、令和5年度欄の373人は現行計画の令和4年度初期値と一致する。現行計画の令和6年度現況値752人は新しい測定値として上書きせず分離する。","review_status":"reviewed","confidence":"high"}],"reviewed_at":"2026-07-21","review_status":"reviewed","confidence":"high"}